README.rst
setup.py
browser_compare/__init__.py
browser_compare.egg-info/PKG-INFO
browser_compare.egg-info/SOURCES.txt
browser_compare.egg-info/dependency_links.txt
browser_compare.egg-info/requires.txt
browser_compare.egg-info/top_level.txt