Metadata-Version: 1.1
Name: browser-compare
Version: 0.0.1
Summary: Library for detecting browser changes
Home-page: https://github.com/ojarva/browser-compare
Author: Olli Jarva
Author-email: olli@jarva.fi
License: MIT
Download-URL: https://github.com/ojarva/browser-compare
Keywords: browser user-agent
Platform: UNKNOWN
Classifier: Development Status :: 3 - Alpha
Classifier: Topic :: Software Development :: Libraries
Classifier: License :: OSI Approved :: MIT License
